<?xml version="1.0" encoding="utf-8" ?>
<dwsync>
<file name="bootstrap-datetimepicker.css" server="new.moic.gov.np/public_html/" local="130645809050092773" remote="130680928800000000" Dst="0" />
<file name="bootstrap-datetimepicker.js" server="new.moic.gov.np/public_html/" local="130645809049872600" remote="130680928800000000" Dst="0" />
<file name="date.js" server="new.moic.gov.np/public_html/" local="130662469087780745" remote="130680928800000000" Dst="0" />
<file name="respond.js" server="new.moic.gov.np/public_html/" local="130645809049782575" remote="130680928800000000" Dst="0" />
<file name="bootstrap-datetimepicker.css" server="new.moic.gov.np/public_html/new/" local="130645809050092773" remote="130717705200000000" Dst="0" />
<file name="bootstrap-datetimepicker.js" server="new.moic.gov.np/public_html/new/" local="130645809049872600" remote="130717705200000000" Dst="0" />
<file name="date.js" server="new.moic.gov.np/public_html/new/" local="130662469087780745" remote="130717705200000000" Dst="0" />
<file name="respond.js" server="new.moic.gov.np/public_html/new/" local="130645809049782575" remote="130717705200000000" Dst="0" />
<file name="bootstrap-datetimepicker.css" server="www.exam.com.np/public_html/" local="130645809050092773" remote="130974519600000000" Dst="0" />
<file name="bootstrap-datetimepicker.js" server="www.exam.com.np/public_html/" local="130645809049872600" remote="130974519600000000" Dst="0" />
<file name="respond.js" server="www.exam.com.np/public_html/" local="130645809049782575" remote="130974519600000000" Dst="0" />
<file name="date.js" server="www.exam.com.np/public_html/" local="130930114954605555" remote="130974519600000000" Dst="0" />
</dwsync>